main.py
mseep_mcp_server_demo-0.1.8.dist-info/METADATA
mseep_mcp_server_demo-0.1.8.dist-info/WHEEL
mseep_mcp_server_demo-0.1.8.dist-info/top_level.txt
mseep_mcp_server_demo-0.1.8.dist-info/RECORD
